MANIFEST.in
README.md
setup.py
django_fresh.egg-info/PKG-INFO
django_fresh.egg-info/SOURCES.txt
django_fresh.egg-info/dependency_links.txt
django_fresh.egg-info/not-zip-safe
django_fresh.egg-info/requires.txt
django_fresh.egg-info/top_level.txt
fresh/__init__.py
fresh/middleware.py
fresh/models.py
fresh/urls.py
fresh/views.py
fresh/static/fresh/js/refresher.js