Metadata-Version: 1.1
Name: django-fresh
Version: 1.0.5
Summary: Auto-refresh your browser when files in your project change.
Home-page: http://github.com/overshard/django-fresh
Author: Isaac Bythewood
Author-email: isaac@bythewood.me
License: Simplified BSD
Download-URL: http://github.com/overshard/django-fresh/downloads
Platform: UNKNOWN
Classifier: Development Status :: 5 - Production/Stable
Classifier: Environment :: Web Environment
Classifier: Intended Audience :: Developers
Classifier: License :: OSI Approved :: BSD License
Classifier: Operating System :: OS Independent
Classifier: Programming Language :: Python
Classifier: Framework :: Django
